openapi/__init__.py
openapi/base.py
openapi/model.py
openapi/naming.py
openapi/registry.py
openapi/schemas/v2.0/schema.json
openapi-2.0.0.dist-info/LICENSE
openapi-2.0.0.dist-info/METADATA
openapi-2.0.0.dist-info/WHEEL
openapi-2.0.0.dist-info/top_level.txt
openapi-2.0.0.dist-info/RECORD
