Metadata-Version: 2.1
Name: openapi
Version: 2.0.0
Summary: Python OpenAPI 2.0 (Swagger) object model
Home-page: https://github.com/globality-corp/openapi
Author: Globality Engineering
Author-email: engineering@globality.com
Keywords: openapi swagger
Classifier: Programming Language :: Python :: 3
Provides-Extra: yaml
Provides-Extra: test
Provides-Extra: lint
Provides-Extra: typehinting
License-File: LICENSE
